geonode/__init__.py
geonode/apps.py
geonode/celery_app.py
geonode/compat.py
geonode/context_processors.py
geonode/custom_translations.py
geonode/decorators.py
geonode/loaders.py
geonode/notifications_backend.py
geonode/notifications_helper.py
geonode/serializer.py
geonode/settings.py
geonode/singleton.py
geonode/sitemap.py
geonode/urls.py
geonode/utils.py
geonode/version.py
geonode/views.py
geonode/wsgi.py
geonode/api/__init__.py
geonode/api/api.py
geonode/api/apps.py
geonode/api/authentication.py
geonode/api/authorization.py
geonode/api/paginator.py
geonode/api/resourcebase_api.py
geonode/api/tests.py
geonode/api/urls.py
geonode/api/views.py
geonode/assets/__init__.py
geonode/assets/admin.py
geonode/assets/apps.py
geonode/assets/handlers.py
geonode/assets/local.py
geonode/assets/models.py
geonode/assets/serializers.py
geonode/assets/tests.py
geonode/assets/urls.py
geonode/assets/utils.py
geonode/assets/views.py
geonode/assets/management/__init__.py
geonode/assets/management/commands/__init__.py
geonode/assets/management/commands/migrate_file_to_assets.py
geonode/assets/migrations/0001_initial.py
geonode/assets/migrations/__init__.py
geonode/assets/tests/data/one.json
geonode/assets/tests/data/three.json
geonode/assets/tests/data/two.json
geonode/base/__init__.py
geonode/base/admin.py
geonode/base/apps.py
geonode/base/auth.py
geonode/base/base_urls.py
geonode/base/bbox_utils.py
geonode/base/enumerations.py
geonode/base/fields.py
geonode/base/forms.py
geonode/base/middleware.py
geonode/base/models.py
geonode/base/populate_test_data.py
geonode/base/tests.py
geonode/base/translation.py
geonode/base/urls.py
geonode/base/utils.py
geonode/base/views.py
geonode/base/widgets.py
geonode/base/api/__init__.py
geonode/base/api/exceptions.py
geonode/base/api/fields.py
geonode/base/api/filters.py
geonode/base/api/mixins.py
geonode/base/api/pagination.py
geonode/base/api/permissions.py
geonode/base/api/serializers.py
geonode/base/api/tests.py
geonode/base/api/urls.py
geonode/static/geonode/css/cookie-law-info/cookie-law-info-gdpr.css
geonode/static/geonode/css/cookie-law-info/cookie-law-info-public.css
geonode/static/geonode/js/cookie-law-info/cookie-law-info-public.js
geonode-5.0.1.dist-info/licenses/AUTHORS
geonode-5.0.1.dist-info/licenses/LICENSE
geonode-5.0.1.dist-info/METADATA
geonode-5.0.1.dist-info/WHEEL
geonode-5.0.1.dist-info/top_level.txt
geonode-5.0.1.dist-info/RECORD
