Metadata-Version: 2.4
Name: GeoNode
Version: 5.0.1
Summary: Application for serving and sharing geospatial data
Home-page: http://geonode.org
Download-URL: https://github.com/GeoNode/geonode/archive/master.zip
Author: GeoNode Developers
Author-email: dev@geonode.org
License: GPL
Keywords: django,geonode
Classifier: Development Status :: 5 - Production/Stable
Classifier: Environment :: Web Environment
Classifier: Framework :: Django
Classifier: Intended Audience :: Developers
Classifier: Operating System :: OS Independent
Classifier: Topic :: Internet :: WWW/HTTP
Classifier: Programming Language :: Python :: 3.10
Requires-Python: >=3.10
License-File: LICENSE
License-File: AUTHORS
Requires-Dist: Pillow==11.3.0
Requires-Dist: lxml==5.2.1
Requires-Dist: psycopg2==2.9.9
Requires-Dist: Django==5.2.8
Requires-Dist: beautifulsoup4==4.12.3
Requires-Dist: hyperlink==21.0.0
Requires-Dist: urllib3==1.26.18
Requires-Dist: Paver==1.3.4
Requires-Dist: python-slugify==8.0.4
Requires-Dist: decorator==5.1.1
Requires-Dist: celery==5.4.0
Requires-Dist: tqdm==4.66.4
Requires-Dist: Deprecated==1.2.14
Requires-Dist: jsonschema==4.22.0
Requires-Dist: zipstream-ng==1.8.0
Requires-Dist: schema==0.7.7
Requires-Dist: rdflib==6.3.2
Requires-Dist: smart_open==7.0.4
Requires-Dist: PyMuPDF==1.26.3
Requires-Dist: defusedxml==0.7.1
Requires-Dist: cachetools==6.2.4
Requires-Dist: django-allauth==0.63.6
Requires-Dist: django-appconf==1.0.6
Requires-Dist: django-filter==24.2
Requires-Dist: django-imagekit==5.0.0
Requires-Dist: django-taggit==5.0.1
Requires-Dist: django-markdownify==0.9.5
Requires-Dist: django-mptt==0.16.0
Requires-Dist: django-modeltranslation==0.18.13
Requires-Dist: django-treebeard==4.7.1
Requires-Dist: django-guardian<2.4.1
Requires-Dist: django-downloadview==2.3.0
Requires-Dist: django-polymorphic==3.1.0
Requires-Dist: django-tastypie<0.15.0
Requires-Dist: django-tinymce==3.7.1
Requires-Dist: django-uuid-upload-path==1.0.0
Requires-Dist: django-widget-tweaks==1.5.0
Requires-Dist: django-sequences==3.0
Requires-Dist: oauthlib==3.3.1
Requires-Dist: pyjwt==2.8.0
Requires-Dist: redis==6.2.0
Requires-Dist: pyproj<3.8.0
Requires-Dist: OWSLib==0.34.1
Requires-Dist: geonode-pycsw==3.0.0b1
Requires-Dist: SQLAlchemy==2.0.30
Requires-Dist: Shapely==2.1.2
Requires-Dist: mercantile==1.2.1
Requires-Dist: numpy==1.26.*
Requires-Dist: Jinja2==3.1.6
Requires-Dist: dj-database-url==2.1.0
Requires-Dist: dj-pagination==2.5.0
Requires-Dist: django-select2==8.4.3
Requires-Dist: django-forms-bootstrap<=3.1.0
Requires-Dist: django-autocomplete-light==3.11.0
Requires-Dist: django-invitations<2.1.1
Requires-Dist: django-recaptcha==4.0.0
Requires-Dist: djangorestframework==3.15.2
Requires-Dist: djangorestframework-gis==1.2.0
Requires-Dist: djangorestframework-guardian==0.3.0
Requires-Dist: drf-extensions==0.7.1
Requires-Dist: drf-spectacular==0.27.2
Requires-Dist: geonode-dynamic-rest==2.3.0.1
Requires-Dist: geonode-pinax-notifications==6.0.0.3
Requires-Dist: django-geonode-mapstore-client==5.0.0
Requires-Dist: django-avatar==8.0.1
Requires-Dist: geonode-oauth-toolkit==2.2.2.2
Requires-Dist: geonode-announcements==2.0.2.2
Requires-Dist: django-activity-stream==2.0.0
Requires-Dist: gn-arcrest==10.5.6
Requires-Dist: geoserver-restconfig==2.0.16
Requires-Dist: gn-gsimporter==2.0.4
Requires-Dist: gisdata==0.5.4
Requires-Dist: setuptools<80,>=59
Requires-Dist: pdok-geopackage-validator==0.14.4
Requires-Dist: geonode-django-dynamic-model==0.4.0
Requires-Dist: django-bootstrap3-datetimepicker-2==2.8.3
Requires-Dist: django-storages==1.14.3
Requires-Dist: dropbox==11.36.2
Requires-Dist: google-cloud-storage==2.16.0
Requires-Dist: boto3==1.39.3
Requires-Dist: whitenoise==6.6.0
Requires-Dist: xmltodict<0.13.1
Requires-Dist: inflection>=0.4.0
Requires-Dist: mock<6.0.0
Requires-Dist: python-dateutil==2.9.0.post0
Requires-Dist: pytz==2024.1
Requires-Dist: requests==2.32.5
Requires-Dist: timeout-decorator==0.5.0
Requires-Dist: pylibmc==1.6.3
Requires-Dist: sherlock==0.4.1
Requires-Dist: GDAL==3.8.4
Requires-Dist: psutil==5.9.8
Requires-Dist: django-cors-headers==4.9.0
Requires-Dist: django-user-agents==0.4.0
Requires-Dist: uWSGI==2.0.30
Requires-Dist: docker==7.0.0
Requires-Dist: invoke==2.2.0
Requires-Dist: coverage==7.5.1
Requires-Dist: requests-toolbelt==1.0.0
Requires-Dist: flake8==7.3.0
Requires-Dist: black==24.4.2
Requires-Dist: pytest==8.2.0
Requires-Dist: pytest-bdd==7.1.2
Requires-Dist: splinter==0.21.0
Requires-Dist: pytest-splinter==3.3.2
Requires-Dist: pytest-django==4.8.0
Requires-Dist: pip==25.0.1
Requires-Dist: pixelmatch==0.3.0
Requires-Dist: factory-boy==3.3.0
Requires-Dist: flaky==3.8.1
Requires-Dist: selenium<5.0.0,>=4.15.1
Requires-Dist: selenium-requests==2.0.4
Requires-Dist: webdriver_manager==4.0.1
Requires-Dist: cryptography==46.0.3
Requires-Dist: jwcrypto>=1.5.6
Dynamic: description
Dynamic: description-content-type
Dynamic: download-url
Dynamic: license-file
